faststt/__init__.py
faststt/faststt.py
faststt-0.1.1.dist-info/licenses/LICENSE
faststt-0.1.1.dist-info/METADATA
faststt-0.1.1.dist-info/WHEEL
faststt-0.1.1.dist-info/top_level.txt
faststt-0.1.1.dist-info/RECORD
