Metadata-Version: 2.4
Name: faststt
Version: 0.1.1
Summary: Hybrid Speech-to-Text using Faster-Whisper and SpeechRecognition
Author-email: Harsharaj <rharsharaj03@gmail.com>
License: MIT
Keywords: STT,speech-to-text,whisper,faster-whisper,microphone,transcription,python-stt,offline-stt,low-latency-stt,speech-recognition
Classifier: Programming Language :: Python :: 3
Classifier: License :: OSI Approved :: MIT License
Classifier: Operating System :: OS Independent
Requires-Python: >=3.10
License-File: LICENSE
Requires-Dist: faster-whisper==1.2.0
Requires-Dist: SpeechRecognition==3.14.3
Requires-Dist: PyAudio==0.2.14
Dynamic: license-file
